waterrocketpy/__init__.py
waterrocketpy/common.py
waterrocketpy/main.py
waterrocketpy/Legacy/Core.py
waterrocketpy/Legacy/__init__.py
waterrocketpy/Legacy/builder_legacy.py
waterrocketpy/Legacy/main.py
waterrocketpy/Legacy/plotter.py
waterrocketpy/analysis/__init__.py
waterrocketpy/analysis/energy_breakdown.py
waterrocketpy/analysis/energy_breakdown_plot.py
waterrocketpy/core/__init__.py
waterrocketpy/core/constants.py
waterrocketpy/core/physics_engine.py
waterrocketpy/core/simulation.py
waterrocketpy/core/validation.py
waterrocketpy/data/MANIFEST.in
waterrocketpy/optimization/__init__.py
waterrocketpy/optimization/water_rocket_optimizer.py
waterrocketpy/rocket/__init__.py
waterrocketpy/rocket/builder.py
waterrocketpy/rocket/geometry.py
waterrocketpy/rocket/materials.py
waterrocketpy/utils/__init__.py
waterrocketpy/utils/loader.py
waterrocketpy/utils/saver.py
waterrocketpy/visualization/__init__.py
waterrocketpy/visualization/debug
waterrocketpy/visualization/flight_animation.py
waterrocketpy/visualization/parameter_explorer.py
waterrocketpy/visualization/parameter_explorer_debugging.py
waterrocketpy/visualization/plot_flight_data.py
waterrocketpy-0.2.1.dist-info/licenses/LICENSE
waterrocketpy-0.2.1.dist-info/METADATA
waterrocketpy-0.2.1.dist-info/WHEEL
waterrocketpy-0.2.1.dist-info/entry_points.txt
waterrocketpy-0.2.1.dist-info/top_level.txt
waterrocketpy-0.2.1.dist-info/RECORD
