Metadata-Version: 2.4
Name: waterrocketpy
Version: 0.2.1
Summary: A modular Python package for simulating water rockets.
Author-email: Pablo M <pablo.marg8@gmail.com>
License: MIT License
Project-URL: Homepage, https://github.com/Cube002/waterrocketpy
Keywords: waterrocketpy
Classifier: Intended Audience :: Developers
Classifier: License :: OSI Approved :: MIT License
Classifier: Natural Language :: English
Classifier: Programming Language :: Python :: 3.8
Classifier: Programming Language :: Python :: 3.9
Classifier: Programming Language :: Python :: 3.10
Classifier: Programming Language :: Python :: 3.11
Classifier: Programming Language :: Python :: 3.12
Requires-Python: >=3.8
License-File: LICENSE
Requires-Dist: numpy
Requires-Dist: scipy
Requires-Dist: matplotlib
Provides-Extra: extra
Requires-Dist: pandas; extra == "extra"
Provides-Extra: dev
Requires-Dist: pytest>=7.0; extra == "dev"
Requires-Dist: pytest-cov; extra == "dev"
Requires-Dist: coverage; extra == "dev"
Requires-Dist: ruff; extra == "dev"
Requires-Dist: mypy; extra == "dev"
Provides-Extra: all
Requires-Dist: waterrocketpy[extra]; extra == "all"
Requires-Dist: waterrocketpy[dev]; extra == "all"
Dynamic: license-file
